dsi6/__init__.py
dsi6/metrics.py
dsi6-0.6.3.3.dist-info/LICENSE
dsi6-0.6.3.3.dist-info/METADATA
dsi6-0.6.3.3.dist-info/WHEEL
dsi6-0.6.3.3.dist-info/top_level.txt
dsi6-0.6.3.3.dist-info/RECORD
