Metadata-Version: 2.1
Name: dsi6
Version: 0.6.3.3
Summary: Mostly metrics right now, by and for dsi students
Home-page: https://github.com/MarkPopovich/dsi6
Author: San Francisco dsi-cc6 cohort, shout out to Ritchie Kwan for providing the final code
Author-email: mpopovich@gmail.com
License: UNKNOWN
Platform: UNKNOWN
Classifier: Programming Language :: Python :: 3
Classifier: License :: OSI Approved :: MIT License
Classifier: Operating System :: OS Independent
